{
  "taxi_data": [
    {
      "country": "Switzerland",
      "startPrice": 7.35,
      "pricePerKm": 4.41
    },
    {
      "country": "Bahrain",
      "startPrice": 5.31,
      "pricePerKm": 3.98
    },
    {
      "country": "Luxembourg",
      "startPrice": 5.42,
      "pricePerKm": 3.85
    },
    {
      "country": "Guyana",
      "startPrice": 2.87,
      "pricePerKm": 3.35
    },
    {
      "country": "Mauritius",
      "startPrice": 3.32,
      "pricePerKm": 3.32
    },
    {
      "country": "Albania",
      "startPrice": 3.27,
      "pricePerKm": 3.27
    },
    {
      "country": "Kuwait",
      "startPrice": 3.24,
      "pricePerKm": 3.24
    },
    {
      "country": "Jamaica",
      "startPrice": 0.95,
      "pricePerKm": 3.17
    },
    {
      "country": "Mozambique",
      "startPrice": 1.88,
      "pricePerKm": 3.13
    },
    {
      "country": "El Salvador",
      "startPrice": 7,
      "pricePerKm": 3
    },
    {
      "country": "Venezuela",
      "startPrice": 4.5,
      "pricePerKm": 3
    },
    {
      "country": "Japan",
      "startPrice": 4.04,
      "pricePerKm": 2.96
    },
    {
      "country": "Germany",
      "startPrice": 5.04,
      "pricePerKm": 2.71
    },
    {
      "country": "Belgium",
      "startPrice": 5.96,
      "pricePerKm": 2.71
    },
    {
      "country": "Netherlands",
      "startPrice": 4.23,
      "pricePerKm": 2.68
    },
    {
      "country": "Saudi Arabia",
      "startPrice": 2.67,
      "pricePerKm": 2.67
    },
    {
      "country": "Barbados",
      "startPrice": 12.5,
      "pricePerKm": 2.5
    },
    {
      "country": "Papua New Guinea",
      "startPrice": 4.95,
      "pricePerKm": 2.47
    },
    {
      "country": "Botswana",
      "startPrice": 0.58,
      "pricePerKm": 2.41
    },
    {
      "country": "Iceland",
      "startPrice": 5.86,
      "pricePerKm": 2.4
    },
    {
      "country": "Dominican Republic",
      "startPrice": 3.19,
      "pricePerKm": 2.39
    },
    {
      "country": "Qatar",
      "startPrice": 2.2,
      "pricePerKm": 2.2
    },
    {
      "country": "Denmark",
      "startPrice": 7.27,
      "pricePerKm": 2.18
    },
    {
      "country": "Malta",
      "startPrice": 5.42,
      "pricePerKm": 2.17
    },
    {
      "country": "Ireland",
      "startPrice": 5.37,
      "pricePerKm": 2.17
    },
    {
      "country": "Austria",
      "startPrice": 5.31,
      "pricePerKm": 2.17
    },
    {
      "country": "United Kingdom",
      "startPrice": 4.92,
      "pricePerKm": 2.13
    },
    {
      "country": "France",
      "startPrice": 4.88,
      "pricePerKm": 2.12
    },
    {
      "country": "Cyprus",
      "startPrice": 6.21,
      "pricePerKm": 2.06
    },
    {
      "country": "Zimbabwe",
      "startPrice": 5,
      "pricePerKm": 2
    },
    {
      "country": "Panama",
      "startPrice": 2.25,
      "pricePerKm": 2
    },
    {
      "country": "Costa Rica",
      "startPrice": 1.82,
      "pricePerKm": 2
    },
    {
      "country": "Mexico",
      "startPrice": 2.49,
      "pricePerKm": 1.99
    },
    {
      "country": "Sweden",
      "startPrice": 5.97,
      "pricePerKm": 1.96
    },
    {
      "country": "New Zealand",
      "startPrice": 2.28,
      "pricePerKm": 1.92
    },
    {
      "country": "Peru",
      "startPrice": 2.18,
      "pricePerKm": 1.91
    },
    {
      "country": "Australia",
      "startPrice": 3.78,
      "pricePerKm": 1.83
    },
    {
      "country": "United States",
      "startPrice": 3.75,
      "pricePerKm": 1.74
    },
    {
      "country": "Colombia",
      "startPrice": 1.51,
      "pricePerKm": 1.7
    },
    {
      "country": "Nigeria",
      "startPrice": 0.89,
      "pricePerKm": 1.69
    },
    {
      "country": "Italy",
      "startPrice": 5.42,
      "pricePerKm": 1.66
    },
    {
      "country": "Ivory Coast",
      "startPrice": 1.65,
      "pricePerKm": 1.65
    },
    {
      "country": "Norway",
      "startPrice": 11.45,
      "pricePerKm": 1.64
    },
    {
      "country": "Chile",
      "startPrice": 0.85,
      "pricePerKm": 1.6
    },
    {
      "country": "Kenya",
      "startPrice": 1.54,
      "pricePerKm": 1.54
    },
    {
      "country": "Uruguay",
      "startPrice": 1.41,
      "pricePerKm": 1.53
    },
    {
      "country": "Iraq",
      "startPrice": 2.29,
      "pricePerKm": 1.52
    },
    {
      "country": "Canada",
      "startPrice": 3.12,
      "pricePerKm": 1.51
    },
    {
      "country": "Lebanon",
      "startPrice": 5,
      "pricePerKm": 1.5
    },
    {
      "country": "Ecuador",
      "startPrice": 1.5,
      "pricePerKm": 1.5
    },
    {
      "country": "Bolivia",
      "startPrice": 1.45,
      "pricePerKm": 1.45
    },
    {
      "country": "Jordan",
      "startPrice": 0.71,
      "pricePerKm": 1.41
    },
    {
      "country": "Spain",
      "startPrice": 3.9,
      "pricePerKm": 1.4
    },
    {
      "country": "Czech Republic",
      "startPrice": 2.16,
      "pricePerKm": 1.39
    },
    {
      "country": "Finland",
      "startPrice": 7.59,
      "pricePerKm": 1.38
    },
    {
      "country": "Palestine",
      "startPrice": 2.73,
      "pricePerKm": 1.36
    },
    {
      "country": "Hong Kong (China)",
      "startPrice": 3.73,
      "pricePerKm": 1.35
    },
    {
      "country": "Slovakia",
      "startPrice": 3.25,
      "pricePerKm": 1.3
    },
    {
      "country": "Slovenia",
      "startPrice": 2.11,
      "pricePerKm": 1.3
    },
    {
      "country": "Paraguay",
      "startPrice": 0.82,
      "pricePerKm": 1.26
    },
    {
      "country": "Ghana",
      "startPrice": 1.42,
      "pricePerKm": 1.24
    },
    {
      "country": "Macao (China)",
      "startPrice": 2.62,
      "pricePerKm": 1.2
    },
    {
      "country": "Hungary",
      "startPrice": 2.98,
      "pricePerKm": 1.19
    },
    {
      "country": "Thailand",
      "startPrice": 1.04,
      "pricePerKm": 1.19
    },
    {
      "country": "Greece",
      "startPrice": 4.34,
      "pricePerKm": 1.14
    },
    {
      "country": "Montenegro",
      "startPrice": 1.08,
      "pricePerKm": 1.08
    },
    {
      "country": "Lithuania",
      "startPrice": 3.25,
      "pricePerKm": 1.08
    },
    {
      "country": "Croatia",
      "startPrice": 3.25,
      "pricePerKm": 1.08
    },
    {
      "country": "Nepal",
      "startPrice": 2.15,
      "pricePerKm": 1.08
    },
    {
      "country": "Portugal",
      "startPrice": 3.79,
      "pricePerKm": 1.07
    },
    {
      "country": "Guatemala",
      "startPrice": 3.73,
      "pricePerKm": 1.04
    },
    {
      "country": "South Africa",
      "startPrice": 1.09,
      "pricePerKm": 1.04
    },
    {
      "country": "Libya",
      "startPrice": 1.04,
      "pricePerKm": 1.04
    },
    {
      "country": "Syria",
      "startPrice": 1,
      "pricePerKm": 1
    },
    {
      "country": "Puerto Rico",
      "startPrice": 8,
      "pricePerKm": 1
    },
    {
      "country": "Argentina",
      "startPrice": 1.47,
      "pricePerKm": 1
    },
    {
      "country": "Serbia",
      "startPrice": 1.85,
      "pricePerKm": 0.93
    },
    {
      "country": "Trinidad And Tobago",
      "startPrice": 1.03,
      "pricePerKm": 0.88
    },
    {
      "country": "Poland",
      "startPrice": 2.07,
      "pricePerKm": 0.88
    },
    {
      "country": "Estonia",
      "startPrice": 3.25,
      "pricePerKm": 0.87
    },
    {
      "country": "Brazil",
      "startPrice": 1.03,
      "pricePerKm": 0.86
    },
    {
      "country": "Malaysia",
      "startPrice": 1.12,
      "pricePerKm": 0.84
    },
    {
      "country": "Bosnia And Herzegovina",
      "startPrice": 1.39,
      "pricePerKm": 0.83
    },
    {
      "country": "Israel",
      "startPrice": 4.53,
      "pricePerKm": 0.82
    },
    {
      "country": "Namibia",
      "startPrice": 0.71,
      "pricePerKm": 0.81
    },
    {
      "country": "Latvia",
      "startPrice": 2.71,
      "pricePerKm": 0.81
    },
    {
      "country": "Oman",
      "startPrice": 3.12,
      "pricePerKm": 0.78
    },
    {
      "country": "Romania",
      "startPrice": 0.83,
      "pricePerKm": 0.76
    },
    {
      "country": "Kosovo (Disputed Territory)",
      "startPrice": 2.17,
      "pricePerKm": 0.76
    },
    {
      "country": "Taiwan",
      "startPrice": 2.58,
      "pricePerKm": 0.76
    },
    {
      "country": "Singapore",
      "startPrice": 3.44,
      "pricePerKm": 0.75
    },
    {
      "country": "Morocco",
      "startPrice": 0.72,
      "pricePerKm": 0.72
    },
    {
      "country": "Bulgaria",
      "startPrice": 1.33,
      "pricePerKm": 0.72
    },
    {
      "country": "Georgia",
      "startPrice": 1.08,
      "pricePerKm": 0.72
    },
    {
      "country": "Kazakhstan",
      "startPrice": 1.2,
      "pricePerKm": 0.7
    },
    {
      "country": "United Arab Emirates",
      "startPrice": 3.27,
      "pricePerKm": 0.68
    },
    {
      "country": "Vietnam",
      "startPrice": 0.72,
      "pricePerKm": 0.63
    },
    {
      "country": "Nicaragua",
      "startPrice": 1.01,
      "pricePerKm": 0.62
    },
    {
      "country": "Turkey",
      "startPrice": 0.87,
      "pricePerKm": 0.62
    },
    {
      "country": "North Macedonia",
      "startPrice": 1.06,
      "pricePerKm": 0.62
    },
    {
      "country": "Mongolia",
      "startPrice": 0.59,
      "pricePerKm": 0.59
    },
    {
      "country": "Azerbaijan",
      "startPrice": 1.76,
      "pricePerKm": 0.59
    },
    {
      "country": "South Korea",
      "startPrice": 3.1,
      "pricePerKm": 0.58
    },
    {
      "country": "Pakistan",
      "startPrice": 0.71,
      "pricePerKm": 0.53
    },
    {
      "country": "Cuba",
      "startPrice": 2.14,
      "pricePerKm": 0.5
    },
    {
      "country": "Cameroon",
      "startPrice": 0.5,
      "pricePerKm": 0.5
    },
    {
      "country": "Fiji",
      "startPrice": 0.87,
      "pricePerKm": 0.44
    },
    {
      "country": "Bangladesh",
      "startPrice": 0.82,
      "pricePerKm": 0.41
    },
    {
      "country": "Algeria",
      "startPrice": 1.08,
      "pricePerKm": 0.39
    },
    {
      "country": "Indonesia",
      "startPrice": 0.61,
      "pricePerKm": 0.37
    },
    {
      "country": "Ukraine",
      "startPrice": 1.92,
      "pricePerKm": 0.36
    },
    {
      "country": "Russia",
      "startPrice": 1.74,
      "pricePerKm": 0.35
    },
    {
      "country": "China",
      "startPrice": 1.38,
      "pricePerKm": 0.35
    },
    {
      "country": "Sri Lanka",
      "startPrice": 0.41,
      "pricePerKm": 0.34
    },
    {
      "country": "Tunisia",
      "startPrice": 0.29,
      "pricePerKm": 0.32
    },
    {
      "country": "Armenia",
      "startPrice": 1.53,
      "pricePerKm": 0.31
    },
    {
      "country": "Belarus",
      "startPrice": 1.16,
      "pricePerKm": 0.31
    },
    {
      "country": "Uzbekistan",
      "startPrice": 0.5,
      "pricePerKm": 0.3
    },
    {
      "country": "Iran",
      "startPrice": 0.5,
      "pricePerKm": 0.3
    },
    {
      "country": "Ethiopia",
      "startPrice": 1.3,
      "pricePerKm": 0.3
    },
    {
      "country": "Egypt",
      "startPrice": 0.39,
      "pricePerKm": 0.3
    },
    {
      "country": "India",
      "startPrice": 0.92,
      "pricePerKm": 0.29
    },
    {
      "country": "Moldova",
      "startPrice": 1.82,
      "pricePerKm": 0.28
    },
    {
      "country": "Tajikistan",
      "startPrice": 0.92,
      "pricePerKm": 0.28
    },
    {
      "country": "Uganda",
      "startPrice": 0.68,
      "pricePerKm": 0.27
    },
    {
      "country": "Philippines",
      "startPrice": 0.79,
      "pricePerKm": 0.26
    },
    {
      "country": "Kyrgyzstan",
      "startPrice": 1.37,
      "pricePerKm": 0.23
    }
  ]
}